Metadata-Version: 2.1
Name: llama-index-readers-dashscope-custom
Version: 0.1.2
Summary: llama-index readers dashscope integration
License: MIT
Author: Your Name
Author-email: you@example.com
Requires-Python: >=3.8.1,<4.0
Classifier: License :: OSI Approved :: MIT License
Classifier: Programming Language :: Python :: 3
Classifier: Programming Language :: Python :: 3.9
Classifier: Programming Language :: Python :: 3.10
Classifier: Programming Language :: Python :: 3.11
Classifier: Programming Language :: Python :: 3.12
Requires-Dist: llama-index-core (>=0.10.0,<0.11.0)
Requires-Dist: oss2 (>=2.18.5,<3.0.0)
Requires-Dist: retrying (>=1.3.4,<2.0.0)
